pyapp_ext/messaging/__init__.py
pyapp_ext/messaging/__version__.py
pyapp_ext/messaging/bases.py
pyapp_ext/messaging/checks.py
pyapp_ext/messaging/default_settings.py
pyapp_ext/messaging/exceptions.py
pyapp_ext/messaging/factory.py
pyapp_ext/messaging/serialisation.py
pyapp_ext/messaging/asyncio/__init__.py
pyapp_ext/messaging/asyncio/bases.py
pyapp_ext/messaging/asyncio/checks.py
pyapp_ext/messaging/asyncio/cli.py
pyapp_ext/messaging/asyncio/factory.py
pyapp_ext/messaging/asyncio/queues.py
pyapp_ext/messaging/cli/__init__.py
pyApp_Messaging-0.2.0.dist-info/LICENSE
pyApp_Messaging-0.2.0.dist-info/METADATA
pyApp_Messaging-0.2.0.dist-info/WHEEL
pyApp_Messaging-0.2.0.dist-info/entry_points.txt
pyApp_Messaging-0.2.0.dist-info/top_level.txt
pyApp_Messaging-0.2.0.dist-info/RECORD
