Metadata-Version: 2.1
Name: pyApp-Messaging
Version: 0.2.0
Summary: Common messaging extension. Provides base messaging services that other service build on
Home-page: https://github.com/pyapp-org/pyapp-messaging
Author: Tim Savage
Author-email: tim@savage.company
License: BSD-3-Clause
Keywords: application,framework
Platform: any
Classifier: Development Status :: 4 - Beta
Classifier: Intended Audience :: Developers
Classifier: License :: OSI Approved :: BSD License
Classifier: Operating System :: OS Independent
Classifier: Topic :: Software Development :: Libraries :: Python Modules
Classifier: Topic :: Software Development :: Libraries :: Application Frameworks
Classifier: Programming Language :: Python :: 3
Classifier: Programming Language :: Python :: 3.6
Classifier: Programming Language :: Python :: 3.7
Classifier: Programming Language :: Python :: Implementation :: CPython
Classifier: Programming Language :: Python :: Implementation :: PyPy
Requires-Python: >=3.6
Requires-Dist: pyapp (>=4.0.5)
Provides-Extra: dev
Requires-Dist: docutils ; extra == 'dev'
Requires-Dist: black ; extra == 'dev'
